PathFile/PathFile.py
PathFile/__init__.py
PathFile-1.1.0.dist-info/LICENCE
PathFile-1.1.0.dist-info/METADATA
PathFile-1.1.0.dist-info/WHEEL
PathFile-1.1.0.dist-info/top_level.txt
PathFile-1.1.0.dist-info/RECORD
