Metadata-Version: 2.1
Name: PathFile
Version: 1.1.0
Summary: This package is PathFile
Home-page: https://github.com/ArtemMurashkin
Author: Murashkin Artem
Author-email: artemmurashkin02@mai.ru
License: UNKNOWN
Platform: any
Requires-Python: >=3.0
Requires-Dist: pypiwin32 (>=223)
